pawtorch/__init__.py
pawtorch/_patch.py
pawtorch-0.1.1.dist-info/METADATA
pawtorch-0.1.1.dist-info/WHEEL
pawtorch-0.1.1.dist-info/top_level.txt
pawtorch-0.1.1.dist-info/RECORD
